<ti:work xmlns:ti="http://chs.harvard.edu/xmlns/cts" groupUrn="urn:cts:croala:jelacic01" urn="urn:cts:croala:jelacic01.croala701288" xml:lang="lat">
  <ti:title xml:lang="lat">Valedictoria.</ti:title>
  <ti:edition workUrn="urn:cts:croala:jelacic01.croala701288" urn="urn:cts:croala:jelacic01.croala701288.croala-lat1:">
    <ti:label xml:lang="lat">Valedictoria, versio electronica.</ti:label>
    <ti:description xml:lang="hrv">Prema kasnijem znanstvenom izdanju (1933).</ti:description>
  </ti:edition>
</ti:work>